CHANGELOG.txt
LICENCE.txt
MANIFEST.in
README.txt
setup.py
pubsams/__init__.py
pubsams.egg-info/PKG-INFO
pubsams.egg-info/SOURCES.txt
pubsams.egg-info/dependency_links.txt
pubsams.egg-info/requires.txt
pubsams.egg-info/top_level.txt