Metadata-Version: 2.1
Name: pubsams
Version: 0.1.160
Summary: Find smilarity between compound and active and inactive compound in bioassay and common substracture
Home-page: 
Author: Ahmed Alhilal
Author-email: aalhilal@kfu.edu
License: MIT
Keywords: chemiformatics,pubchem,conversion
Classifier: Development Status :: 5 - Production/Stable
Classifier: Intended Audience :: Education
Classifier: Operating System :: Microsoft :: Windows :: Windows 10
Classifier: License :: OSI Approved :: MIT License
Classifier: Programming Language :: Python :: 3
License-File: LICENCE.txt
